gemato/__init__.py
gemato/__main__.py
gemato/cli.py
gemato/compression.py
gemato/exceptions.py
gemato/find_top_level.py
gemato/hash.py
gemato/manifest.py
gemato/openpgp.py
gemato/profile.py
gemato/recursiveloader.py
gemato/util.py
gemato/verify.py
gemato-20.11.dist-info/entry_points.txt
gemato-20.11.dist-info/licenses/COPYING
gemato-20.11.dist-info/WHEEL
gemato-20.11.dist-info/METADATA
gemato-20.11.dist-info/RECORD
