Metadata-Version: 2.4
Name: gemato
Version: 20.11
Summary: Gentoo Manifest Tool -- a utility to verify and update Manifest files
Author-email: Michał Górny <mgorny@gentoo.org>
Requires-Python: >=3.9
Classifier: Development Status :: 5 - Production/Stable
Classifier: Environment :: Console
Classifier: Intended Audience :: System Administrators
Classifier: License :: OSI Approved :: GNU General Public License v2 or later (GPLv2+)
Classifier: Operating System :: POSIX
Classifier: Programming Language :: Python :: 3 :: Only
Classifier: Topic :: Security :: Cryptography
License-File: COPYING
Requires-Dist: rich ; extra == "pretty-log"
Requires-Dist: pytest ; extra == "test"
Requires-Dist: pytest ; extra == "test-full"
Requires-Dist: requests ; extra == "test-full"
Requires-Dist: responses ; extra == "test-full"
Requires-Dist: requests ; extra == "wkd-refresh"
Project-URL: Homepage, https://github.com/mgorny/gemato/
Provides-Extra: pretty-log
Provides-Extra: test
Provides-Extra: test-full
Provides-Extra: wkd-refresh
